{
	"@type":"Hierarchy",
	"Name":"S_DF_GENERIQUE_ACI",
	"Elements":
	[
		{
			"Name":"TOT_DF_GEN_ACI",
			"Type":"Consolidated"
		},
		{
			"Name":"COST",
			"Type":"Consolidated"
		},
		{
			"Name":".1",
			"Type":"String"
		},
		{
			"Name":".2",
			"Type":"String"
		},
		{
			"Name":".3",
			"Type":"String"
		},
		{
			"Name":".4",
			"Type":"String"
		},
		{
			"Name":".5",
			"Type":"String"
		},
		{
			"Name":".6",
			"Type":"String"
		},
		{
			"Name":".7",
			"Type":"String"
		},
		{
			"Name":".8",
			"Type":"String"
		},
		{
			"Name":".9",
			"Type":"String"
		},
		{
			"Name":".10",
			"Type":"String"
		},
		{
			"Name":".11",
			"Type":"String"
		},
		{
			"Name":".12",
			"Type":"String"
		},
		{
			"Name":".13",
			"Type":"String"
		},
		{
			"Name":".14",
			"Type":"String"
		},
		{
			"Name":"ASSET",
			"Type":"String"
		},
		{
			"Name":"70",
			"Type":"Numeric"
		},
		{
			"Name":"165",
			"Type":"Numeric"
		},
		{
			"Name":"205",
			"Type":"Numeric"
		},
		{
			"Name":"TOT_AMORTISSEMENT",
			"Type":"Consolidated"
		},
		{
			"Name":"EDP_INTERCO_AMORT",
			"Type":"Consolidated"
		},
		{
			"Name":"-EDP",
			"Type":"Numeric"
		},
		{
			"Name":"-INTERCO",
			"Type":"Numeric"
		}
	],
	"Edges":
	[
		{
			"ParentName":"TOT_DF_GEN_ACI",
			"ComponentName":"ASSET",
			"Weight":1
		},
		{
			"ParentName":"TOT_DF_GEN_ACI",
			"ComponentName":"COST",
			"Weight":1
		},
		{
			"ParentName":"COST",
			"ComponentName":".1",
			"Weight":1
		},
		{
			"ParentName":"COST",
			"ComponentName":".2",
			"Weight":1
		},
		{
			"ParentName":"COST",
			"ComponentName":".3",
			"Weight":1
		},
		{
			"ParentName":"COST",
			"ComponentName":".4",
			"Weight":1
		},
		{
			"ParentName":"COST",
			"ComponentName":".5",
			"Weight":1
		},
		{
			"ParentName":"COST",
			"ComponentName":".6",
			"Weight":1
		},
		{
			"ParentName":"COST",
			"ComponentName":".7",
			"Weight":1
		},
		{
			"ParentName":"COST",
			"ComponentName":".8",
			"Weight":1
		},
		{
			"ParentName":"COST",
			"ComponentName":".9",
			"Weight":1
		},
		{
			"ParentName":"COST",
			"ComponentName":".10",
			"Weight":1
		},
		{
			"ParentName":"COST",
			"ComponentName":".11",
			"Weight":1
		},
		{
			"ParentName":"COST",
			"ComponentName":".12",
			"Weight":1
		},
		{
			"ParentName":"COST",
			"ComponentName":".13",
			"Weight":1
		},
		{
			"ParentName":"COST",
			"ComponentName":".14",
			"Weight":1
		},
		{
			"ParentName":"TOT_AMORTISSEMENT",
			"ComponentName":"70",
			"Weight":1
		},
		{
			"ParentName":"TOT_AMORTISSEMENT",
			"ComponentName":"165",
			"Weight":1
		},
		{
			"ParentName":"TOT_AMORTISSEMENT",
			"ComponentName":"205",
			"Weight":1
		},
		{
			"ParentName":"EDP_INTERCO_AMORT",
			"ComponentName":"-EDP",
			"Weight":1
		},
		{
			"ParentName":"EDP_INTERCO_AMORT",
			"ComponentName":"-INTERCO",
			"Weight":1
		},
		{
			"ParentName":"EDP_INTERCO_AMORT",
			"ComponentName":"TOT_AMORTISSEMENT",
			"Weight":1
		}
	],
	"Subsets@Code.links":
	[
		"S_DF_GENERIQUE_ACI.subsets/COST_PHASE_2.json",
		"S_DF_GENERIQUE_ACI.subsets/LEVEL_0.json",
		"S_DF_GENERIQUE_ACI.subsets/SAISIE_COST_ASSET.json"
	]
}